{
  "db_name": "SQLite",
  "query": "SELECT package, version, depsHasOutdated AS has_outdated, depsLastCheck AS last_check, targets\n            FROM PackageVersion\n            INNER JOIN Package ON PackageVersion.package = Package.name\n            WHERE yanked = FALSE",
  "describe": {
    "columns": [
      {
        "name": "package",
        "ordinal": 0,
        "type_info": "Text"
      },
      {
        "name": "version",
        "ordinal": 1,
        "type_info": "Text"
      },
      {
        "name": "has_outdated",
        "ordinal": 2,
        "type_info": "Bool"
      },
      {
        "name": "last_check",
        "ordinal": 3,
        "type_info": "Datetime"
      },
      {
        "name": "targets",
        "ordinal": 4,
        "type_info": "Text"
      }
    ],
    "parameters": {
      "Right": 0
    },
    "nullable": [
      false,
      false,
      false,
      false,
      false
    ]
  },
  "hash": "5a3925df81fe66e7c0e7ebe187d1cb77b99252d8163addd83ccc297dd7ecb3ad"
}
